nostalgic/__init__.py
nostalgic/nostalgic.py
nostalgic-2.0.0.dist-info/LICENSE
nostalgic-2.0.0.dist-info/METADATA
nostalgic-2.0.0.dist-info/WHEEL
nostalgic-2.0.0.dist-info/top_level.txt
nostalgic-2.0.0.dist-info/RECORD
