Metadata-Version: 2.1
Name: nostalgic
Version: 2.0.0
Summary: A configuration module to save and restore end-user and application settings
Home-page: https://codeberg.org/excalamus/nostalgic
Author: Matt Trzcinski
Author-email: matt@excalamus.com
Project-URL: Bug Reports, https://codeberg.org/excalamus/nostalgic/issues
Project-URL: Funding, https://donate.pypi.org
Project-URL: Source, https://codeberg.org/excalamus/nostalgic
Keywords: settings,configuration,configure,config,development,application
Classifier: Development Status :: 3 - Alpha
Classifier: Intended Audience :: Developers
Classifier: Topic :: Software Development :: Libraries
Classifier: License :: OSI Approved :: MIT License
Classifier: Programming Language :: Python :: 3
Classifier: Programming Language :: Python :: 3.6
Classifier: Programming Language :: Python :: 3.7
Classifier: Programming Language :: Python :: 3.8
Classifier: Programming Language :: Python :: 3.9
Classifier: Programming Language :: Python :: 3.10
Classifier: Programming Language :: Python :: 3 :: Only
Requires-Python: >=3.6
License-File: LICENSE
